omomo/core/__init__.py
omomo/core/quantization/__init__.py
omomo/core/quantization/quantizer_kmeans.py
omomo/core/quantization/torch_helpers.py
omomo/core/quantization/vgg_model.py
omomo/core/types/__init__.py
omomo/core/types/binary_utils.py
omomo/core/types/float_converter.py
omomo/core/types/integer_converter.py
omomo-0.0.1.dist-info/LICENSE
omomo-0.0.1.dist-info/METADATA
omomo-0.0.1.dist-info/WHEEL
omomo-0.0.1.dist-info/RECORD
